cloud_cleaner/__init__.py
cloud_cleaner/config.py
cloud_cleaner/string_matcher.py
cloud_cleaner/bin/__init__.py
cloud_cleaner/bin/entrypoint.py
cloud_cleaner/resources/__init__.py
cloud_cleaner/resources/fip.py
cloud_cleaner/resources/resource.py
cloud_cleaner/resources/server.py
cloud_cleaner-0.1.0.dist-info/DESCRIPTION.rst
cloud_cleaner-0.1.0.dist-info/METADATA
cloud_cleaner-0.1.0.dist-info/RECORD
cloud_cleaner-0.1.0.dist-info/WHEEL
cloud_cleaner-0.1.0.dist-info/entry_points.txt
cloud_cleaner-0.1.0.dist-info/metadata.json
cloud_cleaner-0.1.0.dist-info/top_level.txt
tests/__init__.py
tests/cloud_cleaner/__init__.py
tests/cloud_cleaner/test_config.py
tests/cloud_cleaner/bin/__init__.py
tests/cloud_cleaner/bin/test_entrypoint.py
tests/cloud_cleaner/resources/__init__.py
tests/cloud_cleaner/resources/test_all.py
tests/cloud_cleaner/resources/test_fip.py
tests/cloud_cleaner/resources/test_resource.py
tests/cloud_cleaner/resources/test_server.py
