Metadata-Version: 2.0
Name: cloud-cleaner
Version: 0.1.0
Summary: Utilities to clean up old OpenStack resources
Home-page: https://github.com/greg-hellings/cloud-cleaner
Author: Gregory Hellings
Author-email: greg.hellings@gmail.com
License: BSD
Keywords: cloud,openstack
Platform: UNKNOWN
Classifier: License :: OSI Approved :: BSD License
Classifier: Operating System :: Unix
Classifier: Operating System :: POSIX
Classifier: Operating System :: Microsoft :: Windows
Classifier: Programming Language :: Python
Classifier: Programming Language :: Python :: 2
Classifier: Programming Language :: Python :: 2.7
Classifier: Programming Language :: Python :: 3
Classifier: Programming Language :: Python :: 3.3
Classifier: Programming Language :: Python :: 3.4
Classifier: Programming Language :: Python :: 3.5
Classifier: Programming Language :: Python :: 3.6
Classifier: Programming Language :: Python :: Implementation :: CPython
Classifier: Programming Language :: Python :: Implementation :: PyPy
Classifier: Topic :: Utilities
Requires-Dist: shade
Requires-Dist: os-client-config
Requires-Dist: munch
Requires-Dist: pytz
Requires-Dist: py2-ipaddress; python_version<'3.3'
